odoo/addons/product_total_weight_from_packaging/README.rst
odoo/addons/product_total_weight_from_packaging/__init__.py
odoo/addons/product_total_weight_from_packaging/__manifest__.py
odoo/addons/product_total_weight_from_packaging/i18n/es.po
odoo/addons/product_total_weight_from_packaging/i18n/it.po
odoo/addons/product_total_weight_from_packaging/i18n/product_total_weight_from_packaging.pot
odoo/addons/product_total_weight_from_packaging/models/__init__.py
odoo/addons/product_total_weight_from_packaging/models/product.py
odoo/addons/product_total_weight_from_packaging/readme/CONTRIBUTORS.md
odoo/addons/product_total_weight_from_packaging/readme/CREDITS.md
odoo/addons/product_total_weight_from_packaging/readme/DESCRIPTION.md
odoo/addons/product_total_weight_from_packaging/static/description/icon.png
odoo/addons/product_total_weight_from_packaging/static/description/index.html
odoo/addons/product_total_weight_from_packaging/tests/__init__.py
odoo/addons/product_total_weight_from_packaging/tests/test_product_total_weight_from_packaging.py
odoo_addon_product_total_weight_from_packaging-18.0.1.0.0.2.dist-info/METADATA
odoo_addon_product_total_weight_from_packaging-18.0.1.0.0.2.dist-info/WHEEL
odoo_addon_product_total_weight_from_packaging-18.0.1.0.0.2.dist-info/top_level.txt
odoo_addon_product_total_weight_from_packaging-18.0.1.0.0.2.dist-info/RECORD
